ketl/__init__.py
ketl/cli.py
ketl/ketl.py
ketl/db/__init__.py
ketl/db/models.py
ketl/db/settings.py
ketl/etl/Pipeline.py
ketl/etl/__init__.py
ketl/extractor/Extractor.py
ketl/extractor/Rest.py
ketl/extractor/__init__.py
ketl/loader/Loader.py
ketl/loader/__init__.py
ketl/transformer/Transformer.py
ketl/transformer/__init__.py
ketl/utils/__init__.py
ketl/utils/db_utils.py
ketl/utils/file_utils.py
ketl-0.1.6.dist-info/AUTHORS.rst
ketl-0.1.6.dist-info/LICENSE
ketl-0.1.6.dist-info/METADATA
ketl-0.1.6.dist-info/WHEEL
ketl-0.1.6.dist-info/entry_points.txt
ketl-0.1.6.dist-info/top_level.txt
ketl-0.1.6.dist-info/RECORD
