Metadata-Version: 2.1
Name: ketl
Version: 0.1.6
Summary: konfigurable ETL
Home-page: https://github.com/grapesmoker/ketl
Author: Jerry Vinokurov
Author-email: grapesmoker@gmail.com
License: MIT license
Keywords: ketl
Platform: UNKNOWN
Classifier: Development Status :: 2 - Pre-Alpha
Classifier: Intended Audience :: Developers
Classifier: License :: OSI Approved :: MIT License
Classifier: Natural Language :: English
Classifier: Programming Language :: Python :: 3
Classifier: Programming Language :: Python :: 3.5
Classifier: Programming Language :: Python :: 3.6
Classifier: Programming Language :: Python :: 3.7
Classifier: Programming Language :: Python :: 3.8
Requires-Python: >=3.5
License-File: LICENSE
License-File: AUTHORS.rst
Requires-Dist: Click (>=7.0)
Requires-Dist: furl (~=2.1.0)
Requires-Dist: smart-open (~=5.2.1)
Requires-Dist: marshmallow (~=3.14.1)
Requires-Dist: tqdm (~=4.62.3)
Requires-Dist: pyarrow (~=6.0.0)
Requires-Dist: requests (~=2.26.0)
Requires-Dist: sqlalchemy (~=1.4.27)
Requires-Dist: pandas (~=1.3.4)
Requires-Dist: inflection (~=0.5.1)
Requires-Dist: more-itertools (~=8.7.0)
